msmart/__init__.py
msmart/base_command.py
msmart/cli.py
msmart/client.py
msmart/cloud.py
msmart/const.py
msmart/crc8.py
msmart/lan.py
msmart/packet_builder.py
msmart/scanner.py
msmart/security.py
msmart/utils.py
msmart/device/__init__.py
msmart/device/base.py
msmart/device/AC/__init__.py
msmart/device/AC/appliance.py
msmart/device/AC/command.py
msmart/device/DB/__init__.py
msmart/device/DB/appliance.py
msmart/device/DB/command.py
msmart-0.2.5.dist-info/LICENSE
msmart-0.2.5.dist-info/METADATA
msmart-0.2.5.dist-info/WHEEL
msmart-0.2.5.dist-info/entry_points.txt
msmart-0.2.5.dist-info/top_level.txt
msmart-0.2.5.dist-info/RECORD
