Metadata-Version: 2.1
Name: msmart
Version: 0.2.5
Summary: A library to control Midea appliances via the Local area network
Home-page: https://github.com/mac-zhou/midea-msmart
Author: mac_zhou
Author-email: mac.zfl@gmail.com
License: MIT
Classifier: Programming Language :: Python :: 3
Classifier: License :: OSI Approved :: MIT License
Classifier: Operating System :: OS Independent
License-File: LICENSE
Requires-Dist: click
Requires-Dist: pycryptodome
Requires-Dist: requests
Requires-Dist: ifaddr
